complexPyTorch/__init__.py
complexPyTorch/complexFunctions.py
complexPyTorch/complexLayers.py
complexPyTorch-0.3.dist-info/LICENSE
complexPyTorch-0.3.dist-info/METADATA
complexPyTorch-0.3.dist-info/WHEEL
complexPyTorch-0.3.dist-info/top_level.txt
complexPyTorch-0.3.dist-info/RECORD
