Metadata-Version: 2.1
Name: complexPyTorch
Version: 0.3
Summary: A high-level toolbox for using complex valued neural networks in PyTorch.
Home-page: https://gitlab.institut-langevin.espci.fr/spopoff/complexPyTorch
Author: Sebastien M. Popoff
Author-email: sebastien.popoff@espci.psl.eu
License: MIT License
Keywords: pytorch,deep learning,complex values
Platform: UNKNOWN
Classifier: 
Requires-Python: >=3.6
Requires-Dist: torch
